django_example/__init__.py
django_example/admin_views.py
django_example/apps.py
django_example/asgi.py
django_example/management/__init__.py
django_example/management/commands/__init__.py
django_example/management/commands/run_testserver.py
django_example/publish.py
django_example/settings/__init__.py
django_example/settings/base.py
django_example/settings/local.py
django_example/settings/prod.py
django_example/settings/test.py
django_example/templates/django_example/debug_view.html
django_example/tests/__init__.py
django_example/tests/test_django_project.py
django_example/tests/test_example_project_urls_1.snapshot.html
django_example/tests/test_project_setup.py
django_example/tests/test_utils.py
django_example/tests/test_views_debug.py
django_example/tests/test_views_debug_urls_1.snapshot.html
django_example/tests/test_views_login_required.py
django_example/urls.py
django_example/views.py
django_example/wsgi.py
django_example-0.2.0.dist-info/entry_points.txt
django_example-0.2.0.dist-info/LICENSE
django_example-0.2.0.dist-info/WHEEL
django_example-0.2.0.dist-info/METADATA
django_example-0.2.0.dist-info/RECORD
