Metadata-Version: 2.1
Name: django-example
Version: 0.2.0
Summary: Demo YunoHost Application to demonstrate the integration of a Django project under YunoHost.
Home-page: https://github.com/jedie/django_example
License: GPL-3.0-or-later
Author: Jens Diemer
Author-email: django-example@jensdiemer.de
Maintainer: Jens Diemer
Maintainer-email: django-example@jensdiemer.de
Requires-Python: >=3.9,<4.0.0
Classifier: License :: OSI Approved :: GNU General Public License v3 or later (GPLv3+)
Classifier: Programming Language :: Python :: 3
Classifier: Programming Language :: Python :: 3.9
Classifier: Programming Language :: Python :: 3.10
Classifier: Programming Language :: Python :: 3.11
Requires-Dist: bx_django_utils
Project-URL: Bug Tracker, https://github.com/jedie/django_example/issues
